gitiii/__init__.py
gitiii/attention.py
gitiii/calculate_PCC.py
gitiii/dataloader.py
gitiii/embedding.py
gitiii/estimator.py
gitiii/find_ligands.py
gitiii/model.py
gitiii/network_analyzer.py
gitiii/predictor.py
gitiii/preprocess.py
gitiii/process_dataset.py
gitiii/spatial_visualizer.py
gitiii/subtyping_analyzer.py
gitiii/test.py
gitiii/trainer.py
gitiii/data/__init__.py
gitiii/data/interactions_human.pth
gitiii/data/interactions_human_nonichenetv2.pth
gitiii/data/interactions_mouse.pth
gitiii/data/interactions_mouse_nonichenetv2.pth
gitiii-0.1.0.dist-info/LICENSE
gitiii-0.1.0.dist-info/METADATA
gitiii-0.1.0.dist-info/WHEEL
gitiii-0.1.0.dist-info/top_level.txt
gitiii-0.1.0.dist-info/RECORD
