Metadata-Version: 2.1
Name: gitiii
Version: 0.1.0
Summary: Investigation of pair-wise single cell interactions through statistically interpreting spatial cell state correlations learned by self-supervised graph inductive bias transformer
Home-page: https://github.com/lugia.xiao/gitiii
Author: Xiao Xiao
Author-email: Xiao Xiao <xiao.xiao.xx244@yale.edu>
License: GPL-3.0
Classifier: License :: OSI Approved :: GNU General Public License v3 (GPLv3)
Classifier: Programming Language :: Python :: 3.7
Classifier: Programming Language :: Python :: 3.8
Classifier: Programming Language :: Python :: 3.9
Classifier: Operating System :: OS Independent
Requires-Python: >=3.6
License-File: LICENSE
Requires-Dist: torch
Requires-Dist: pandas
Requires-Dist: monotonicnetworks
Requires-Dist: scipy
Requires-Dist: scanpy
Requires-Dist: anndata
Requires-Dist: statsmodels
Requires-Dist: scikit-learn
Requires-Dist: numpy
Requires-Dist: matplotlib
Requires-Dist: maxfuse
Requires-Dist: seaborn
